genuine/__init__.py
genuine/data_list.py
genuine/data_list.txt
genuine/fake.py
genuine_fake-1.2.24.dist-info/METADATA
genuine_fake-1.2.24.dist-info/WHEEL
genuine_fake-1.2.24.dist-info/top_level.txt
genuine_fake-1.2.24.dist-info/RECORD
