Metadata-Version: 2.1
Name: genuine-fake
Version: 1.2.24
Summary: Get genuine data for your testing requirements.
Home-page: https://github.com/xeroxzen/genuine-fake
Author: Andile Jaden Mbele
Author-email: andilembele020@gmail.com
Classifier: License :: OSI Approved :: MIT License
Classifier: Programming Language :: Python :: 3
Classifier: Programming Language :: Python :: 3.11
Classifier: Programming Language :: Python :: 3.12
Classifier: Development Status :: 5 - Production/Stable
Classifier: Intended Audience :: Developers
Classifier: Topic :: Software Development :: Testing
Classifier: Topic :: Software Development :: Libraries :: Python Modules
Requires-Python: >=3.7
